aiga_amqp/__init__.py
aiga_amqp/apps.py
aiga_amqp/core.py
aiga_amqp/tests.py
aiga_django_amqp-0.0.1.dist-info/LICENSE
aiga_django_amqp-0.0.1.dist-info/METADATA
aiga_django_amqp-0.0.1.dist-info/WHEEL
aiga_django_amqp-0.0.1.dist-info/top_level.txt
aiga_django_amqp-0.0.1.dist-info/RECORD
