Metadata-Version: 2.1
Name: aiga-django-amqp
Version: 0.0.1
Summary: Django app yang digunakan untuk mempermudah penggunaan rabbit mq
Home-page: https://github.com/ariksubagia/aiga-django-amqp
Author: I Putu Arik Subagia, S.kom
Author-email: ariksubagia@ymail.com
License: MIT
Platform: UNKNOWN
Classifier: Environment :: Web Environment
Classifier: Framework :: Django
Classifier: Framework :: Django :: 3.0
Classifier: Intended Audience :: Developers
Classifier: License :: OSI Approved :: MIT License
Classifier: Operating System :: OS Independent
Classifier: Programming Language :: Python
Classifier: Programming Language :: Python :: 3
Classifier: Programming Language :: Python :: 3 :: Only
Classifier: Programming Language :: Python :: 3.8
Classifier: Programming Language :: Python :: 3.9
Classifier: Topic :: Internet :: WWW/HTTP
Classifier: Topic :: Internet :: WWW/HTTP :: Dynamic Content
Requires-Python: >=3.9
License-File: LICENSE
Requires-Dist: Django (>=3.0)
Requires-Dist: Pika (>=1.2.1)
